oidcish/__init__.py
oidcish/conn.py
oidcish/crypt.py
oidcish/flows/base.py
oidcish/flows/code.py
oidcish/flows/credentials.py
oidcish/flows/device.py
oidcish/models.py
oidcish-1.0.3.dist-info/METADATA
oidcish-1.0.3.dist-info/WHEEL
oidcish-1.0.3.dist-info/RECORD
