Metadata-Version: 2.1
Name: oidcish
Version: 1.0.3
Summary: Obtain authentication tokens from OIDC providers.
Author: Erik G. Brandt
Author-email: erik.brandt@shaarpec.com
Requires-Python: >=3.10,<4.0
Classifier: Programming Language :: Python :: 3
Classifier: Programming Language :: Python :: 3.10
Classifier: Programming Language :: Python :: 3.11
Requires-Dist: StrEnum (>=0.4.15,<0.5.0)
Requires-Dist: background (>=0.2.1,<0.3.0)
Requires-Dist: beautifulsoup4 (>=4.12.2,<5.0.0)
Requires-Dist: cryptography (>=41.0.1,<42.0.0)
Requires-Dist: httpx (>=0.24.1,<0.25.0)
Requires-Dist: pendulum (>=2.1.2,<3.0.0)
Requires-Dist: pkce (>=1.0.3,<2.0.0)
Requires-Dist: pydantic (>=2.0.2,<3.0.0)
Requires-Dist: pydantic-settings (>=2.0.1,<3.0.0)
Requires-Dist: python-dotenv (>=1.0.0,<2.0.0)
Requires-Dist: python-jose (>=3.3.0,<4.0.0)
